mcp_crawl/server.py
mcp_crawl-0.1.2.dist-info/METADATA
mcp_crawl-0.1.2.dist-info/WHEEL
mcp_crawl-0.1.2.dist-info/entry_points.txt
mcp_crawl-0.1.2.dist-info/top_level.txt
mcp_crawl-0.1.2.dist-info/RECORD
