Metadata-Version: 2.4
Name: mcp-crawl
Version: 0.1.2
Summary: A web crawler using Model Context Protocol (MCP)
License: MIT
Requires-Python: >=3.11
Requires-Dist: mcp[cli]>=1.7.1
Requires-Dist: fastmcp>=2.2.7
Requires-Dist: anyio>=3.7.1
Requires-Dist: click>=8.1.7
Requires-Dist: starlette>=0.28.0
Requires-Dist: uvicorn>=0.23.2
Requires-Dist: crawl4ai>=0.5.0
Requires-Dist: httpx>=0.24.1
Requires-Dist: lxml>=4.9.3
Requires-Dist: playwright>=1.41.0
Provides-Extra: dev
Requires-Dist: pytest>=7.0.0; extra == "dev"
Requires-Dist: black>=23.0.0; extra == "dev"
Requires-Dist: isort>=5.12.0; extra == "dev"
Requires-Dist: mypy>=1.0.0; extra == "dev"
Requires-Dist: ruff>=0.0.1; extra == "dev"
